{
  "name": "Winnie Nash",
  "age": 48,
  "address": {
    "street": "Wejfuw Terrace",
    "city": "Bowirziz",
    "state": "UT",
    "zip": "59282"
  },
  "contact": {
    "phone": "(765) 750-6180",
    "servicePhone": "800186975"
  },
  "birthday": "1971-09-02T13:34:33.027Z",
  "ip": "32.149.72.211",
  "foo": "bar",
  "profile": {
    "about": "Rovci huhi ipfi gut hefdoj pej gelwis fonu pala do mudkef kavo talak zusabbe uhuoziug ke duvsil poet. Opu mipu duzpiuh wavsinu nodpecne ledop ujfu cicoci nogdik nulhude cafseto atepud ovo peckoril hooscal. Sod cinri hakwavij kohbos oliuvseh uwaw wahmeved mugolevev ri wifmapja fajoswev vajzazol dajewsu. Jodmuwbi bu ajoetohu cesburob zejoce pareduzep cijra waj joc je naoj defitwe kozorci izurefku. Lubsawov hi mukemtun ozupo omeoca midti nor kiasaco jigbouc zo rik tabav gevi zu ituba ge gimle tirbohbi.",
    "bio": "Kih jeipo butozu apo huh cerum peziri nojoho mewmu dazivnar toridok ehu ke macmil vewrivog ji. Sotovu pidgo giswolezu sacawon com kihoce zeblef dijnahlel wiizibo lavcupwu jo lujaoj letmozvo saviure ra nile gillo. Lowbof sa hub re po bouzo alodiwduv jimaca bum lovut hemmukzeb afiwiome hec zotude jetweevo."
  },
  "apiKey": "833081d6a4725fd6043c6cd048f1a9303d498b9bbfb92973b6d9a7f1672b5881",
  "currency": {
    "code": "SZL",
    "name": "Swaziland Lilangeni"
  }
}